<odoo>
    <!-- Add text for donation receipts -->
    <record id="view_events_thank_donation" model="ir.ui.view">
        <field name="name">crm.event.compassion.thankyou.form</field>
        <field name="model">crm.event.compassion</field>
        <field name="inherit_id" ref="crm_compassion.view_events_form"/>
        <field name="arch" type="xml">
            <notebook>
                <page string="Donation Receipts">
                    <field name="thank_you_text" widget="html" options="{'style-inline': true}"/>
                </page>
                <page string="4M registrations">
                    <group col="6">
                        <field name="muskathlon_event_id" colspan="4"/><label string="" nolabel="1" colspan="2"/>
                    </group>
                    <group>
                        <field name="muskathlon_registration_ids" context="{'default_event_id': id}">
                            <tree>
                                <field name="partner_id"/>
                                <field name="muskathlon_participant_id"/>
                                <field name="reg_id"/>
                            </tree>
                        </field>
                    </group>
                </page>
            </notebook>
        </field>
    </record>
</odoo>
