<odoo>
    <data noupdate="1">
        <record id="event_letter_template" model="mail.template">
            <field name="name">Event Donation - Thank You Letter</field>
            <field name="model_id" ref="partner_communication.model_partner_communication_job"/>
            <field name="email_from">compassion@compassion.ch</field>
            <field name="reply_to">info@compassion.ch</field>
            <field name="use_default_to" eval="True"/>
            <field name="subject">Donation Receipt</field>
            <field name="body_html" type="html">
                <div>
                    % set invoice_lines = object.get_objects()
                    % set donations = invoice_lines.get_donations()
                    % set partner = object.partner_id
                    % set ambassadors = invoice_lines.mapped('user_id').filtered('ambassador_quote')
                </div>
                <div>
                    ${partner.salutation},
                    <br/>
                    <br/>
                    Compassion Switzerland thank you so much for your generous donation of CHF ${donations[0]}.- you made
                    % if donations[1]:
                        % if len(ambassadors) == 1:
                            <!-- space --> for ${ambassadors.firstname} ${ambassadors.lastname}
                        % else:
                            <!-- space --> (${donations[1]}).
                        % endif
                    % else
                        .
                    % endif
                    <br/>
                    <br/>
                    % if len(ambassadors) == 1:
                        <div id="ambassador_quote">
                            ${ambassadors.ambassador_quote |safe}
                        </div>
                    % endif
                    % if object.event_id.thank_you_text:
                        ${object.event_id.thank_you_text |safe}
                    % endif
                    % if partner.number_sponsorships:
                        Did you write to your child recently? Our new website allows you to write a letter online.
                        Why not take advantage of this and write a letter this week?
                    % else:
                        % if partner.is_new_donor:
                            Since 1952, Compassion has one goal: free as much as possible children from extreme poverty.
                            In partnership with 7'000 local churches, we can support and help 1.8 million children in 25 countries from the South.
                            <br/>
                            <br/>
                        % endif
                            Do you have a heart for children in need? Compassion offers you various ways to contribute.
                            One is through the sponsorship. You can find information in French, German and Italian on our website www.compassion.ch
                            or call us at 0800 874 773.
                    % endif
                    <br/>
                    <br/>
                    Thanks again for your generosity towards the children in need.
                    <br/>
                    <br/>
                    Yours sincerely
                </div>
            </field>
        </record>
    </data>
</odoo>
